imecilabt_utils/__init__.py
imecilabt_utils/bash_quote_util.py
imecilabt_utils/sentry_utils.py
imecilabt_utils/urn_util.py
imecilabt_utils/utils.py
imecilabt_utils/validation_utils.py
imecilabt_utils-1.6.0.dist-info/LICENSE
imecilabt_utils-1.6.0.dist-info/METADATA
imecilabt_utils-1.6.0.dist-info/WHEEL
imecilabt_utils-1.6.0.dist-info/top_level.txt
imecilabt_utils-1.6.0.dist-info/RECORD
