Metadata-Version: 2.1
Name: imecilabt-utils
Version: 1.6.0
Summary: A collection of functions useful in various projects iLab.t projects.
Home-page: https://gitlab.ilabt.imec.be/ilabt/imecilabt-py-utils
Author: Wim Van de Meerssche
Author-email: wim.vandemeerssche@ugent.be
License: MIT
Platform: UNKNOWN
Classifier: License :: OSI Approved :: MIT License
Classifier: Programming Language :: Python :: 3
Requires-Python: >=3.5
License-File: LICENSE
